colorconverter.py
mindpowered_colorconverter/ColorConverter.py
mindpowered_colorconverter/__init__.py
mindpowered_colorconverter-0.0.6.dist-info/LICENSE.txt
mindpowered_colorconverter-0.0.6.dist-info/METADATA
mindpowered_colorconverter-0.0.6.dist-info/WHEEL
mindpowered_colorconverter-0.0.6.dist-info/top_level.txt
mindpowered_colorconverter-0.0.6.dist-info/RECORD
