Metadata-Version: 2.1
Name: mindpowered-colorconverter
Version: 0.0.6
Summary: Converter to convert between various color systems such as RGB, CIELAB, CMYK, HEX, RGB, and XYZ
Home-page: https://mindpowered.dev/
Author: Mind Powered Corporation
Author-email: support@mindpowered.dev
License: MIT
Platform: UNKNOWN
Classifier: Programming Language :: Python :: 3
Classifier: Operating System :: OS Independent
Classifier: License :: OSI Approved :: MIT License
Requires-Dist: mindpowered-maglev
